playing_card_utils/__init__.py
playing_card_utils/card.py
playing_card_utils/card_type.py
playing_card_utils/deck.py
playing_card_utils/exceptions.py
playing_card_utils/suites.py
playing_card_utils-3.3.0.dist-info/LICENSE
playing_card_utils-3.3.0.dist-info/METADATA
playing_card_utils-3.3.0.dist-info/WHEEL
playing_card_utils-3.3.0.dist-info/RECORD
